{
  "Package": {
    "Name": "Weather Forecast Launch Pad",
    "Description": "A weather forecast launch pad that consists of a machine learning-derived forecast dashboard for a specified location and a route forecast application powered by Habistack and Geocodio APIs.",
    "Image": "https://www.fathym.com/assets/images/logo.png",
    "PreviewImage": "https://www.fathym.com/assets/images/logo.png",
    "Intents": [
      "Smart Building",
      "Habistack",
      "Launch Control",
      "Getting Started",
      "IoT",
      "Azure Cloud"
    ]
  },
  "Configurations": {
    "Basic": {
      "Name": "Weather Forecast Launch Pad",
      "Description": "A weather forecast launch pad that consists of a machine learning-derived forecast dashboard for a specified location and a route forecast application powered by Habistack and Geocodio APIs.",
      "Phases": [
        {
          "Name": "Configuring Weather Forecast Launch Pad",
          "Order": 1,
          "Asset": "configure"
        }
      ]
    }
  }
}